LICENSE
MANIFEST.in
README.rst
setup.py
sphinxcontrib/__init__.py
sphinxcontrib/menesbuilder.py
sphinxcontrib_menesbuilder.egg-info/PKG-INFO
sphinxcontrib_menesbuilder.egg-info/SOURCES.txt
sphinxcontrib_menesbuilder.egg-info/dependency_links.txt
sphinxcontrib_menesbuilder.egg-info/namespace_packages.txt
sphinxcontrib_menesbuilder.egg-info/not-zip-safe
sphinxcontrib_menesbuilder.egg-info/requires.txt
sphinxcontrib_menesbuilder.egg-info/top_level.txt