Metadata-Version: 1.1
Name: sphinxcontrib-menesbuilder
Version: 0.1
Summary: menesbuilder is a Sphinx extension for menes PDF generates web application
Home-page: http://menes-pdf.info
Author: WAKAYAMA shirou
Author-email: shirou.faw at gmail.com
License: BSD License
Download-URL: http://pypi.python.org/pypi/sphinxcontrib-menesbuilder
Keywords: sphinx,pdf
Platform: UNKNOWN
Classifier: Development Status :: 3 - Alpha
Classifier: License :: OSI Approved :: BSD License
Classifier: Programming Language :: Python :: 2.7
Classifier: Topic :: Software Development :: Documentation
Classifier: Topic :: Documentation
